[
  {
    "word": "camaraderie",
    "definition": "n.情谊，友情"
  },
  {
    "word": "unqualified",
    "definition": "adj.不受限制的，完全的；不合格的，无资格的"
  },
  {
    "word": "objective",
    "definition": "adj.客观公正的"
  },
  {
    "word": "bridle",
    "definition": "n.马勒；马笼头；v.约束，抑制"
  },
  {
    "word": "paltry",
    "definition": "adj.微不足道的，不重要的"
  },
  {
    "word": "chimera",
    "definition": "n.妄想，幻想"
  },
  {
    "word": "unfounded",
    "definition": "adj.无根据的"
  },
  {
    "word": "opprobrium",
    "definition": "n.谴责，抨击；耻辱"
  },
  {
    "word": "foundation",
    "definition": "n.创立；基础"
  },
  {
    "word": "manipulate",
    "definition": "v.控制，操纵"
  },
  {
    "word": "luxuriant",
    "definition": "adj.繁茂的；丰富的，华丽的"
  },
  {
    "word": "inevitable",
    "definition": "adj.不可避免的，必然的"
  },
  {
    "word": "insightful",
    "definition": "adj.有深刻见解的，富有洞察力的"
  },
  {
    "word": "zealous",
    "definition": "adj.热情的，狂热的"
  },
  {
    "word": "boast",
    "definition": "v.夸耀，吹嘘"
  },
  {
    "word": "trivial",
    "definition": "adj.琐碎的，微不足道的，不重要的"
  },
  {
    "word": "perfunctory",
    "definition": "adj.敷衍的，潦草的"
  },
  {
    "word": "ambivalent",
    "definition": "adj.矛盾的，犹豫不决的"
  },
  {
    "word": "sycophant",
    "definition": "n.阿谀奉承的人，马屁精"
  },
  {
    "word": "irresistible",
    "definition": "adj.无法抗拒的，极为诱人的"
  },
  {
    "word": "fickle",
    "definition": "adj.善变的，变化无常的"
  },
  {
    "word": "expansion",
    "definition": "n.扩张，增加"
  },
  {
    "word": "narcissism",
    "definition": "n.自恋"
  },
  {
    "word": "haphazard",
    "definition": "adj.任意的，杂乱无章的"
  },
  {
    "word": "omnipresent",
    "definition": "adj.无处不在的"
  },
  {
    "word": "urbane",
    "definition": "adj.温文尔雅的，彬彬有礼的"
  },
  {
    "word": "exonerate",
    "definition": "v.免除责任，宣布无罪"
  },
  {
    "word": "stun",
    "definition": "v.使震惊，使目瞪口呆"
  },
  {
    "word": "vaporize",
    "definition": "v.蒸发"
  },
  {
    "word": "partisan",
    "definition": "n.党徒（盲目偏袒某人或某事物的人）；adj.党派的，有偏见的"
  },
  {
    "word": "fixate",
    "definition": "v.使固定；注视"
  },
  {
    "word": "simplicity",
    "definition": "n.简洁，朴素"
  },
  {
    "word": "slight",
    "definition": "adj.微小的，微不足道的；v.轻视，蔑视"
  },
  {
    "word": "sordid",
    "definition": "adj.肮脏的，污秽的；卑劣的，可耻的"
  },
  {
    "word": "lionize",
    "definition": "v.崇拜，将…奉为名人"
  },
  {
    "word": "indispensable",
    "definition": "adj.不可或缺的"
  },
  {
    "word": "timely",
    "definition": "adj.及时的，适时的"
  },
  {
    "word": "dilatory",
    "definition": "adj.拖拉的，延误的"
  },
  {
    "word": "fallacious",
    "definition": "adj.谬误的"
  },
  {
    "word": "teem",
    "definition": "v.充满"
  }
]